camera_signs_detection/__init__.py
camera_signs_detection/__main__.py
camera_signs_detection/detect_signs.py
camera_signs_detection/logger.py
camera_signs_detection/_config/__init__.py
camera_signs_detection/_config/config.py
camera_signs_detection/abstract/__init__.py
camera_signs_detection/abstract/analyzer.py
camera_signs_detection/abstract/image_processor.py
camera_signs_detection/components/__init__.py
camera_signs_detection/components/analyzer.py
camera_signs_detection/components/image_processor.py
camera_signs_detection/data_models/__init__.py
camera_signs_detection/data_models/polygon.py
camera_signs_detection/errors/__init__.py
camera_signs_detection/model/__init__.py
camera_signs_detection/tests/__init__.py
camera_signs_detection/tests/test_analyzer.py
camera_signs_detection/tests/test_image_processor.py
camera_signs_detection/utils/__init__.py
camera_signs_detection/utils/utils.py
inviansignsdetection/__init__.py
inviansignsdetection/__main__.py
inviansignsdetection/detect_signs.py
inviansignsdetection/logger.py
inviansignsdetection/_config/__init__.py
inviansignsdetection/_config/config.py
inviansignsdetection/abstract/__init__.py
inviansignsdetection/abstract/analyzer.py
inviansignsdetection/abstract/image_processor.py
inviansignsdetection/components/__init__.py
inviansignsdetection/components/analyzer.py
inviansignsdetection/components/image_processor.py
inviansignsdetection/data_models/__init__.py
inviansignsdetection/data_models/polygon.py
inviansignsdetection/errors/__init__.py
inviansignsdetection/model/__init__.py
inviansignsdetection/tests/__init__.py
inviansignsdetection/tests/test_analyzer.py
inviansignsdetection/tests/test_image_processor.py
inviansignsdetection/utils/__init__.py
inviansignsdetection/utils/utils.py
signs_detection/__init__.py
signs_detection/__main__.py
signs_detection/detect_signs.py
signs_detection/logger.py
signs_detection/_config/__init__.py
signs_detection/_config/config.py
signs_detection/abstract/__init__.py
signs_detector-0.0.3.dist-info/METADATA
signs_detector-0.0.3.dist-info/WHEEL
signs_detector-0.0.3.dist-info/top_level.txt
signs_detector-0.0.3.dist-info/RECORD
