Metadata-Version: 2.1
Name: signs-detector
Version: 0.0.3
Summary: Super tool
Author: Invian Development team
Author-email: your.email@example.com
Keywords: python,first package
Classifier: Development Status :: 2 - Pre-Alpha
Classifier: Intended Audience :: Developers
Classifier: License :: OSI Approved :: MIT License
Classifier: Programming Language :: Python :: 3.11
Requires-Dist: numpy ==1.25.2
Requires-Dist: opencv-python ==4.8.0.76
Requires-Dist: onnxruntime ==1.15.1
